Metadata-Version: 1.0
Name: cls-distributions
Version: 0.1
Summary: Gaussian distributions
Home-page: UNKNOWN
Author: Mo Shabahang
Author-email: dymax1010@gmail.com
License: UNKNOWN
Platform: UNKNOWN
